xnatclient/__init__.py
xnatclient/xnatclient.py
xnatclient-0.3.0.dist-info/LICENSE
xnatclient-0.3.0.dist-info/METADATA
xnatclient-0.3.0.dist-info/WHEEL
xnatclient-0.3.0.dist-info/top_level.txt
xnatclient-0.3.0.dist-info/RECORD
